Metadata-Version: 2.1
Name: chromatics
Version: 0.1.1
Summary: simple analysis of chromatographic data
Home-page: https://github.com/corinwagen/chromatics
Author: Corin Wagen
Author-email: corin.wagen@gmail.com
License: GPL 3.0
Platform: UNKNOWN
Classifier: Programming Language :: Python :: 3
Classifier: Development Status :: 3 - Alpha
Classifier: Intended Audience :: Science/Research
Requires-Python: >=3.7
